OpenPGPKeyAnalyzer/OpenPGPKeyAnalyzerApp.py
OpenPGPKeyAnalyzer/__init__.py
OpenPGPKeyAnalyzer/Application/KeyParser.py
OpenPGPKeyAnalyzer/Application/__init__.py
OpenPGPKeyAnalyzer/Application/DSAChecks/DSAAnalyzer.py
OpenPGPKeyAnalyzer/Application/ECCChecks/ECCAnalyzer.py
OpenPGPKeyAnalyzer/Application/ElGamalChecks/ElGamalAnalyzer.py
OpenPGPKeyAnalyzer/Application/GeneralChecks/DeprecatedKeyVersionCheck.py
OpenPGPKeyAnalyzer/Application/GeneralChecks/KeyLengthAnalyzer.py
OpenPGPKeyAnalyzer/Application/RSAChecks/FermatFactoringChecks.py
OpenPGPKeyAnalyzer/Application/RSAChecks/LowPrivateExponentRSAChecks.py
OpenPGPKeyAnalyzer/Application/RSAChecks/LowPublicExponentRSACheck.py
OpenPGPKeyAnalyzer/Application/RSAChecks/ROCAChecks.py
OpenPGPKeyAnalyzer/Application/RSAChecks/RSAAnalyzer.py
OpenPGPKeyAnalyzer/Application/Settings/AlterSettings.py
OpenPGPKeyAnalyzer/Application/Tests/Unittests.py
OpenPGPKeyAnalyzer/Application/Util/CreateWeaknessJSON.py
OpenPGPKeyAnalyzer/Application/Util/GeneralInformation.py
OpenPGPKeyAnalyzer-0.1.10.dist-info/LICENSE
OpenPGPKeyAnalyzer-0.1.10.dist-info/METADATA
OpenPGPKeyAnalyzer-0.1.10.dist-info/WHEEL
OpenPGPKeyAnalyzer-0.1.10.dist-info/entry_points.txt
OpenPGPKeyAnalyzer-0.1.10.dist-info/top_level.txt
OpenPGPKeyAnalyzer-0.1.10.dist-info/RECORD
