Metadata-Version: 2.2
Name: OpenPGPKeyAnalyzer
Version: 0.1.10
Summary: Check OpenPGP Key files for known cryptographic vulnerabilities
Author: Alexander Bleicher
License: MIT
Project-URL: Repository, https://github.com/AlexBleicher/OpenPGP-Key-Analyzer
Keywords: security,cryptography,OpenPGP
Classifier: Programming Language :: Python :: 3
Classifier: Operating System :: OS Independent
Requires-Python: >=3.12
License-File: LICENSE
Requires-Dist: cffi
Requires-Dist: coloredlogs
Requires-Dist: cryptography
Requires-Dist: future
Requires-Dist: gmpy2
Requires-Dist: humanfriendly
Requires-Dist: pgpdump
Requires-Dist: pgpy
Requires-Dist: pyasn1
Requires-Dist: pycparser
Requires-Dist: pyreadline3
Requires-Dist: python-dateutil
Requires-Dist: roca-detect
Requires-Dist: setuptools
Requires-Dist: six
